{"assets/images/background.png":["assets/images/background.png"],"assets/images/basket.png":["assets/images/basket.png"],"assets/images/full_robot.png":["assets/images/full_robot.png"],"assets/images/poster_one.png":["assets/images/poster_one.png"],"assets/images/poster_three.png":["assets/images/poster_three.png"],"assets/images/poster_two.png":["assets/images/poster_two.png"],"assets/images/profile_one.png":["assets/images/profile_one.png"],"assets/images/profile_two.png":["assets/images/profile_two.png"],"assets/images/robot.png":["assets/images/robot.png"],"assets/images/volume.png":["assets/images/volume.png"],"assets/svg/cloudupload.svg":["assets/svg/cloudupload.svg"],"assets/svg/coloredsoundwaves.svg":["assets/svg/coloredsoundwaves.svg"],"assets/svg/logout.svg":["assets/svg/logout.svg"],"assets/svg/nextIcon.svg":["assets/svg/nextIcon.svg"],"assets/svg/personicon.svg":["assets/svg/personicon.svg"],"assets/svg/playIcon.svg":["assets/svg/playIcon.svg"],"assets/svg/previousIcon.svg":["assets/svg/previousIcon.svg"],"assets/svg/soundwaves.svg":["assets/svg/soundwaves.svg"],"packages/cupertino_icons/assets/CupertinoIcons.ttf":["packages/cupertino_icons/assets/CupertinoIcons.ttf"]}